[
    {
        "type": "UTGÅENDE_DOKUMENT",
        "mottatt": "2023-01-31T09:17:24",
        "saksnummer": "352011079",
        "tittel": "Opphør Foreldrepenger",
        "url": "https://foreldrepengesoknad-api.dev.nav.no/rest/dokument/hent-dokument/598115880/624862996"
    },
    {
        "type": "UTGÅENDE_DOKUMENT",
        "mottatt": "2023-01-31T09:17:13",
        "saksnummer": "352011080",
        "tittel": "Innvilgelsesbrev Foreldrepenger",
        "url": "https://foreldrepengesoknad-api.dev.nav.no/rest/dokument/hent-dokument/598115879/624862995"
    },
    {
        "type": "INNGÅENDE_DOKUMENT",
        "mottatt": "2023-01-31T09:11:56",
        "saksnummer": "352011080",
        "tittel": "Søknad om foreldrepenger ved fødsel",
        "url": "https://foreldrepengesoknad-api.dev.nav.no/rest/dokument/hent-dokument/598115877/624862992"
    },
    {
        "type": "INNGÅENDE_DOKUMENT",
        "mottatt": "2023-01-31T09:11:56",
        "saksnummer": "352011080",
        "tittel": "Bekreftelse på ventet fødselsdato",
        "url": "https://foreldrepengesoknad-api.dev.nav.no/rest/dokument/hent-dokument/598115877/624862993"
    },
    {
        "type": "UTGÅENDE_DOKUMENT",
        "mottatt": "2023-01-31T09:09:48",
        "saksnummer": "352011079",
        "tittel": "Innvilgelsesbrev Foreldrepenger",
        "url": "https://foreldrepengesoknad-api.dev.nav.no/rest/dokument/hent-dokument/598115875/624862990"
    },
    {
        "type": "INNGÅENDE_DOKUMENT",
        "mottatt": "2023-01-31T09:06:48",
        "saksnummer": "352011079",
        "tittel": "Søknad om foreldrepenger ved fødsel",
        "url": "https://foreldrepengesoknad-api.dev.nav.no/rest/dokument/hent-dokument/598115874/624862989"
    },
    {
        "type": "INNGÅENDE_DOKUMENT",
        "mottatt": "2023-01-31T09:06:48",
        "saksnummer": "352011079",
        "tittel": "Bekreftelse på ventet fødselsdato",
        "url": "https://foreldrepengesoknad-api.dev.nav.no/rest/dokument/hent-dokument/598115877/624862993"
    }
]
