{
    "søknad": {
        "type": "foreldrepenger",
        "harGodkjentVilkår": true,
        "søkersituasjon": {
            "situasjon": "fødsel",
            "rolle": "far"
        },
        "barn": {
            "type": "ufødt",
            "antallBarn": 1,
            "termindato": "2023-05-10T00:00:00.000Z"
        },
        "annenForelder": {
            "etternavn": "sdfsdf",
            "fornavn": "MOR",
            "fnr": "02068629902",
            "utenlandskFnr": false,
            "kanIkkeOppgis": false,
            "harRettPåForeldrepengerINorge": true,
            "harRettPåForeldrepengerIEØS": false,
            "erInformertOmSøknaden": true
        },
        "søker": {
            "erAleneOmOmsorg": false,
            "språkkode": "nb",
            "harHattAnnenInntektSiste10Mnd": false,
            "harJobbetSomFrilansSiste10Mnd": false,
            "harJobbetSomSelvstendigNæringsdrivendeSiste10Mnd": false,
            "andreInntekterSiste10Mnd": [],
            "selvstendigNæringsdrivendeInformasjon": []
        },
        "informasjonOmUtenlandsopphold": {
            "iNorgeNeste12Mnd": true,
            "iNorgeSiste12Mnd": true,
            "tidligereOpphold": [],
            "senereOpphold": []
        },
        "erEndringssøknad": false,
        "dekningsgrad": "100",
        "uttaksplan": [
            {
                "type": "info",
                "infotype": "uttakAnnenPart",
                "id": "62994652-0284-27608-7685-0884387978405",
                "årsak": "UTTAK_FEDREKVOTE_ANNEN_FORELDER",
                "tidsperiode": {
                    "fom": "2022-12-12T00:00:00.000Z",
                    "tom": "2023-02-17T00:00:00.000Z"
                },
                "forelder": "mor",
                "overskrives": true,
                "gradert": false,
                "ønskerSamtidigUttak": true,
                "samtidigUttakProsent": "100",
                "visPeriodeIPlan": true
            },
            {
                "type": "info",
                "infotype": "uttakAnnenPart",
                "id": "344121478-0389-3541-11559-08696299708647",
                "årsak": "UTTAK_FELLESP_ANNEN_FORELDER",
                "tidsperiode": {
                    "fom": "2023-02-20T00:00:00.000Z",
                    "tom": "2023-03-03T00:00:00.000Z"
                },
                "forelder": "mor",
                "overskrives": true,
                "gradert": false,
                "ønskerSamtidigUttak": true,
                "samtidigUttakProsent": "50",
                "visPeriodeIPlan": true
            },
            {
                "id": "2072214629-3653-07154-2905-64890553229679",
                "type": "periodeUtenUttak",
                "tidsperiode": {
                    "fom": "2023-03-06T00:00:00.000Z",
                    "tom": "2023-03-17T00:00:00.000Z"
                }
            },
            {
                "type": "info",
                "infotype": "uttakAnnenPart",
                "id": "003004732-5636-06429-4963-845093517124",
                "årsak": "UTTAK_FEDREKVOTE_ANNEN_FORELDER",
                "tidsperiode": {
                    "fom": "2023-03-20T00:00:00.000Z",
                    "tom": "2023-03-31T00:00:00.000Z"
                },
                "forelder": "mor",
                "overskrives": true,
                "gradert": false,
                "ønskerSamtidigUttak": false,
                "visPeriodeIPlan": true
            },
            {
                "id": "098742541-19499-15417-21299-7684577816910",
                "type": "periodeUtenUttak",
                "tidsperiode": {
                    "fom": "2023-04-03T00:00:00.000Z",
                    "tom": "2023-05-09T00:00:00.000Z"
                }
            },
            {
                "id": "0373420422-0742-3610-8171-5312105011314",
                "forelder": "farMedmor",
                "konto": "FEDREKVOTE",
                "tidsperiode": {
                    "fom": "2023-05-10T00:00:00.000Z",
                    "tom": "2023-05-23T00:00:00.000Z"
                },
                "type": "uttak",
                "erArbeidstaker": false,
                "gradert": false,
                "orgnumre": [],
                "ønskerSamtidigUttak": true,
                "samtidigUttakProsent": "100",
                "vedlegg": []
            }
        ],
        "harGodkjentOppsummering": true,
        "vedlegg": [],
        "tilleggsopplysninger": {},
        "ønskerJustertUttakVedFødsel": false
    },
    "version": 5,
    "currentRoute": "/soknad/oppsummering",
    "uttaksplanInfo": {
        "permisjonStartdato": "2023-05-10"
    },
    "antallUkerIUttaksplan": 49,
    "eksisterendeSak": {
        "saksnummer": "",
        "erAnnenPartsSak": true,
        "grunnlag": {
            "dekningsgrad": "100",
            "antallBarn": 1,
            "morErAleneOmOmsorg": false,
            "morErUfør": false,
            "morHarRett": true,
            "farMedmorErAleneOmOmsorg": false,
            "farMedmorHarRett": true,
            "søkerErFarEllerMedmor": true,
            "termindato": "2023-05-10",
            "erDeltUttak": true,
            "erBarnetFødt": false,
            "familiehendelseDato": "2023-05-10",
            "familiehendelseType": "TERM",
            "harAnnenForelderTilsvarendeRettEØS": false,
            "barn": []
        },
        "saksperioder": [
            {
                "guid": "2882915433-18176-5844-1582-144080848706440",
                "periode": {
                    "fom": "2022-12-12",
                    "tom": "2023-02-17"
                },
                "gjelderAnnenPart": true,
                "resultat": {
                    "innvilget": true,
                    "trekkerMinsterett": true,
                    "trekkerDager": true,
                    "årsak": "ANNET"
                },
                "kontoType": "FEDREKVOTE",
                "flerbarnsdager": false,
                "samtidigUttak": 100
            },
            {
                "guid": "684817013-18706-14690-06404-23185176993949",
                "periode": {
                    "fom": "2023-02-20",
                    "tom": "2023-03-05"
                },
                "gjelderAnnenPart": true,
                "resultat": {
                    "innvilget": true,
                    "trekkerMinsterett": true,
                    "trekkerDager": true,
                    "årsak": "ANNET"
                },
                "kontoType": "FELLESPERIODE",
                "flerbarnsdager": false,
                "samtidigUttak": 50
            },
            {
                "guid": "133591420-01017-5463-8846-15341930228275",
                "periode": {
                    "fom": "2023-03-20",
                    "tom": "2023-03-31"
                },
                "gjelderAnnenPart": true,
                "resultat": {
                    "innvilget": true,
                    "trekkerMinsterett": true,
                    "trekkerDager": true,
                    "årsak": "ANNET"
                },
                "kontoType": "FEDREKVOTE",
                "flerbarnsdager": false
            }
        ],
        "uttaksplan": [
            {
                "type": "info",
                "infotype": "uttakAnnenPart",
                "id": "62994652-0284-27608-7685-0884387978405",
                "årsak": "UTTAK_FEDREKVOTE_ANNEN_FORELDER",
                "tidsperiode": {
                    "fom": "2022-12-12T00:00:00.000Z",
                    "tom": "2023-02-17T00:00:00.000Z"
                },
                "forelder": "mor",
                "overskrives": true,
                "gradert": false,
                "ønskerSamtidigUttak": true,
                "samtidigUttakProsent": "100",
                "visPeriodeIPlan": true
            },
            {
                "type": "info",
                "infotype": "uttakAnnenPart",
                "id": "344121478-0389-3541-11559-08696299708647",
                "årsak": "UTTAK_FELLESP_ANNEN_FORELDER",
                "tidsperiode": {
                    "fom": "2023-02-20T00:00:00.000Z",
                    "tom": "2023-03-03T00:00:00.000Z"
                },
                "forelder": "mor",
                "overskrives": true,
                "gradert": false,
                "ønskerSamtidigUttak": true,
                "samtidigUttakProsent": "50",
                "visPeriodeIPlan": true
            },
            {
                "type": "info",
                "infotype": "uttakAnnenPart",
                "id": "003004732-5636-06429-4963-845093517124",
                "årsak": "UTTAK_FEDREKVOTE_ANNEN_FORELDER",
                "tidsperiode": {
                    "fom": "2023-03-20T00:00:00.000Z",
                    "tom": "2023-03-31T00:00:00.000Z"
                },
                "forelder": "mor",
                "overskrives": true,
                "gradert": false,
                "ønskerSamtidigUttak": false,
                "visPeriodeIPlan": true
            }
        ]
    },
    "perioderSomSkalSendesInn": [
        {
            "id": "0373420422-0742-3610-8171-5312105011314",
            "forelder": "farMedmor",
            "konto": "FEDREKVOTE",
            "tidsperiode": {
                "fom": "2023-05-10T00:00:00.000Z",
                "tom": "2023-05-23T00:00:00.000Z"
            },
            "type": "uttak",
            "erArbeidstaker": false,
            "gradert": false,
            "orgnumre": [],
            "ønskerSamtidigUttak": true,
            "samtidigUttakProsent": "100",
            "vedlegg": []
        }
    ],
    "harUttaksplanBlittSlettet": false,
    "søknadGjelderEtNyttBarn": true,
    "brukerSvarteJaPåAutoJustering": false,
    "annenPartsUttakErLagtTilIPlan": true
}